pbutils/__init__.py
pbutils/_version.py
pbutils/cli.py
pbutils/enum_choice.py
pbutils/html2md.py
pbutils/pb2html.py
pbutils-0.1.1.dist-info/LICENSE
pbutils-0.1.1.dist-info/METADATA
pbutils-0.1.1.dist-info/WHEEL
pbutils-0.1.1.dist-info/entry_points.txt
pbutils-0.1.1.dist-info/top_level.txt
pbutils-0.1.1.dist-info/RECORD
