Metadata-Version: 2.1
Name: pbutils
Version: 0.1.1
Summary: MacOS paste board utilities
Author-email: NAKATA Keisuke <keisuke.nakata.919@gmail.com>
License: MIT License
Requires-Python: >=3.10
License-File: LICENSE
Requires-Dist: click >=8.1
Requires-Dist: loguru >=0.7
Requires-Dist: pyobjc >=9.2
Requires-Dist: markdownify >=0.11.6
Provides-Extra: dev
Requires-Dist: black ==23.9.1 ; extra == 'dev'
Requires-Dist: build ==1.0.3 ; extra == 'dev'
Requires-Dist: click ==8.1.7 ; extra == 'dev'
Requires-Dist: colorlog ==4.8.0 ; extra == 'dev'
Requires-Dist: dacite ==1.8.1 ; extra == 'dev'
Requires-Dist: exceptiongroup ==1.1.3 ; extra == 'dev'
Requires-Dist: flake8 ==6.1.0 ; extra == 'dev'
Requires-Dist: gitdb ==4.0.10 ; extra == 'dev'
Requires-Dist: gitpython ==3.1.36 ; extra == 'dev'
Requires-Dist: iniconfig ==2.0.0 ; extra == 'dev'
Requires-Dist: isort ==5.12.0 ; extra == 'dev'
Requires-Dist: mccabe ==0.7.0 ; extra == 'dev'
Requires-Dist: mypy ==1.5.1 ; extra == 'dev'
Requires-Dist: mypy-extensions ==1.0.0 ; extra == 'dev'
Requires-Dist: packaging ==23.1 ; extra == 'dev'
Requires-Dist: pathspec ==0.11.2 ; extra == 'dev'
Requires-Dist: pip-tools ==7.3.0 ; extra == 'dev'
Requires-Dist: platformdirs ==3.10.0 ; extra == 'dev'
Requires-Dist: pluggy ==1.3.0 ; extra == 'dev'
Requires-Dist: pycodestyle ==2.11.0 ; extra == 'dev'
Requires-Dist: pyflakes ==3.1.0 ; extra == 'dev'
Requires-Dist: pyproject-hooks ==1.0.0 ; extra == 'dev'
Requires-Dist: pysen ==0.10.5 ; extra == 'dev'
Requires-Dist: pytest ==7.4.2 ; extra == 'dev'
Requires-Dist: smmap ==5.0.1 ; extra == 'dev'
Requires-Dist: tomli ==2.0.1 ; extra == 'dev'
Requires-Dist: tomlkit ==0.12.1 ; extra == 'dev'
Requires-Dist: typing-extensions ==4.8.0 ; extra == 'dev'
Requires-Dist: unidiff ==0.7.5 ; extra == 'dev'
Requires-Dist: wheel ==0.41.2 ; extra == 'dev'
